realnet_core/__init__.py
realnet_core/action.py
realnet_core/data.py
realnet_core/datamemstore.py
realnet_core/datastore.py
realnet_core/item.py
realnet_core/itemmemstore.py
realnet_core/itemstore.py
realnet_core/provider.py
realnet_core/receiver.py
realnet_core/stream.py
realnet_core/transformer.py
realnet_core/type.py
realnet_core-0.0.13.dist-info/LICENSE
realnet_core-0.0.13.dist-info/METADATA
realnet_core-0.0.13.dist-info/WHEEL
realnet_core-0.0.13.dist-info/entry_points.txt
realnet_core-0.0.13.dist-info/top_level.txt
realnet_core-0.0.13.dist-info/RECORD
