Metadata-Version: 2.1
Name: realnet-core
Version: 0.0.13
Summary: Realnet core
Home-page: https://github.com/virtual-space/realnet-core
Author: Marko Laban
Author-email: marko.laban@l33tsystems.com
License: BSD
Platform: UNKNOWN
Classifier: License :: OSI Approved :: BSD License
Classifier: Programming Language :: Python :: 3
Classifier: Programming Language :: Python :: 3.7
